<?xml version="1.0" standalone="yes"?>  <DATAPACKET Version="2.0"><METADATA><FIELDS><FIELD attrname="USERID" fieldtype="i4"/><FIELD attrname="GRPID" fieldtype="i4"/><FIELD attrname="LOGIN" fieldtype="string" WIDTH="24"/><FIELD attrname="PASS" fieldtype="string" WIDTH="24"/><FIELD attrname="NAME" fieldtype="string" WIDTH="128"/><FIELD attrname="SYSNAME" fieldtype="string" WIDTH="48"/></FIELDS><PARAMS/></METADATA><ROWDATA><ROW USERID="0" GRPID="1" LOGIN="admin" PASS="" NAME="Internal Administrator" SYSNAME="SYSDBA"/><ROW USERID="3" LOGIN="serg" PASS="1" NAME="sergggg" SYSNAME="USER3"/><ROW USERID="4" LOGIN="serg" PASS="1" NAME="s55" SYSNAME="USER4"/><ROW USERID="10" LOGIN="2" PASS="2" NAME="2" SYSNAME="USER10"/><ROW USERID="11" LOGIN="1" PASS="1" NAME="1" SYSNAME="USER101"/><ROW USERID="12" LOGIN="1" PASS="1" NAME="1" SYSNAME="USER102"/><ROW USERID="13" LOGIN="serg" PASS="1" NAME="serg" SYSNAME="USER103"/><ROW USERID="14" LOGIN="admin" PASS="1" NAME="admin" SYSNAME="USER104"/><ROW USERID="15" LOGIN="admin1" PASS="1" NAME="admin1" SYSNAME="USER105"/><ROW USERID="16" LOGIN="1" PASS="1" NAME="1" SYSNAME="USER106"/><ROW USERID="17" LOGIN="1" PASS="1" NAME="1" SYSNAME="USER107"/><ROW USERID="18" LOGIN="A" PASS="1" NAME="A" SYSNAME="USER108"/><ROW USERID="19" LOGIN="A" PASS="1" NAME="A" SYSNAME="USER109"/><ROW USERID="20" LOGIN="A" PASS="1" NAME="A" SYSNAME="USER110"/><ROW USERID="21" LOGIN="A" PASS="1" NAME="A" SYSNAME="USER111"/><ROW USERID="22" LOGIN="A" PASS="1" NAME="A" SYSNAME="USER112"/></ROWDATA></DATAPACKET>